odoo/addons/helpdesk_ticket_parent/README.rst
odoo/addons/helpdesk_ticket_parent/__init__.py
odoo/addons/helpdesk_ticket_parent/__manifest__.py
odoo/addons/helpdesk_ticket_parent/i18n/ca_ES.po
odoo/addons/helpdesk_ticket_parent/i18n/es.po
odoo/addons/helpdesk_ticket_parent/models/__init__.py
odoo/addons/helpdesk_ticket_parent/models/helpdesk_ticket.py
odoo/addons/helpdesk_ticket_parent/static/description/icon.png
odoo/addons/helpdesk_ticket_parent/tests/__init__.py
odoo/addons/helpdesk_ticket_parent/tests/test_helpdesk_ticket_massive_creation_wizard.py
odoo/addons/helpdesk_ticket_parent/views/helpdesk_ticket_view.xml
odoo/addons/helpdesk_ticket_parent/wizards/__init__.py
odoo/addons/helpdesk_ticket_parent/wizards/helpdesk_set_child_ticket/__init__.py
odoo/addons/helpdesk_ticket_parent/wizards/helpdesk_set_child_ticket/helpdesk_ticket_massive_creation_parents_view.xml
odoo/addons/helpdesk_ticket_parent/wizards/helpdesk_set_child_ticket/helpdesk_ticket_set_child_ticket.py
odoo/addons/helpdesk_ticket_parent/wizards/helpdesk_ticket_massive_creation/__init__.py
odoo/addons/helpdesk_ticket_parent/wizards/helpdesk_ticket_massive_creation/helpdesk_ticket_massive_creation.py
odoo/addons/helpdesk_ticket_parent/wizards/helpdesk_ticket_massive_creation/helpdesk_ticket_massive_creation_parents.py
odoo/addons/helpdesk_ticket_parent/wizards/helpdesk_ticket_massive_creation/helpdesk_ticket_massive_creation_parents_view.xml
odoo/addons/helpdesk_ticket_parent/wizards/helpdesk_ticket_massive_creation/helpdesk_ticket_massive_creation_view.xml
odoo/addons/helpdesk_ticket_parent/wizards/send_global_email/__init__.py
odoo/addons/helpdesk_ticket_parent/wizards/send_global_email/helpdesk_ticket_parent_global_send.py
odoo/addons/helpdesk_ticket_parent/wizards/send_global_email/helpdesk_ticket_parent_global_send.xml
odoo/addons/helpdesk_ticket_parent/wizards/send_global_email/helpdesk_ticket_parent_global_send_translations.py
odoo12_addon_helpdesk_ticket_parent-12.0.0.1.0.dist-info/METADATA
odoo12_addon_helpdesk_ticket_parent-12.0.0.1.0.dist-info/WHEEL
odoo12_addon_helpdesk_ticket_parent-12.0.0.1.0.dist-info/top_level.txt
odoo12_addon_helpdesk_ticket_parent-12.0.0.1.0.dist-info/RECORD
